breakout_garden_exporter-2.2.0.data/scripts/breakout-garden-exporter
breakout_garden_exporter-2.2.0.dist-info/licenses/LICENSE
breakoutgardenexporter/__init__.py
breakoutgardenexporter/arguments.py
breakoutgardenexporter/bme280.py
breakoutgardenexporter/icp10125.py
breakoutgardenexporter/metrics.py
breakoutgardenexporter/pm25.py
breakoutgardenexporter/scd4x.py
breakoutgardenexporter/sensor.py
breakoutgardenexporter/sensor_manager.py
breakoutgardenexporter/server.py
breakoutgardenexporter/sgp30.py
tests/__init__.py
tests/test_arguments.py
tests/test_bme280.py
tests/test_icp10125.py
tests/test_metrics.py
tests/test_pm25.py
tests/test_scd4x.py
tests/test_sensor_manager.py
tests/test_sgp30.py
breakout_garden_exporter-2.2.0.dist-info/METADATA
breakout_garden_exporter-2.2.0.dist-info/WHEEL
breakout_garden_exporter-2.2.0.dist-info/top_level.txt
breakout_garden_exporter-2.2.0.dist-info/RECORD
