Metadata-Version: 2.4
Name: breakout-garden-exporter
Version: 2.2.0
Summary: Exposes Prometheus metrics based on data collected from Pimoroni Breakout Garden sensors
Home-page: https://github.com/andrewjw/breakout-garden-exporter
Author: Andrew Wilkinson
Author-email: andrewjwilkinson@gmail.com
Classifier: Programming Language :: Python :: 3.10
Classifier: Programming Language :: Python :: 3.11
Classifier: Programming Language :: Python :: 3.12
Classifier: Programming Language :: Python :: 3.13
Classifier: Programming Language :: Python :: 3.14
Classifier: License :: OSI Approved :: GNU General Public License v3 (GPLv3)
Classifier: Operating System :: OS Independent
Requires-Python: >=3.10
License-File: LICENSE
Requires-Dist: pycodestyle==2.14.0
Requires-Dist: coverage==7.10.7
Requires-Dist: python-semantic-release==10.5.3
Requires-Dist: mypy==1.19.1
Requires-Dist: icp10125==1.0.0
Requires-Dist: pimoroni-sgp30==0.0.2
Requires-Dist: pimoroni-bme280==1.0.0
Requires-Dist: smbus2==0.6.0
Requires-Dist: wheel==0.45.1
Requires-Dist: twine==6.2.0
Requires-Dist: adafruit-circuitpython-pm25==2.1.22
Requires-Dist: scd4x==0.0.2
Dynamic: author
Dynamic: author-email
Dynamic: classifier
Dynamic: description
Dynamic: description-content-type
Dynamic: home-page
Dynamic: license-file
Dynamic: requires-dist
Dynamic: requires-python
Dynamic: summary
